计算机组成原理实验/lab1/srcs/alu.v
module alu #(parameter WIDTH = 32)
            (input [WIDTH - 1: 0] a,
             input [WIDTH - 1: 0] b,      // 两操作数
             input [2:0] s,               // 功能选择
             output reg [WIDTH - 1: 0] y, // 运算结果
             output reg [2:0] f);         // 标志
    
    wire a_s, b_s;
    assign a_s = ~a[WIDTH - 1];
    assign b_s = ~b[WIDTH - 1];
    
    always @(*) begin
        f = 3'b000;
        y = 0;
        case (s)
            3'b000: y = a - b;
            3'b001: y = a + b;
            3'b010: y = a & b;
            3'b011: y = a | b;
            3'b100: y = a ^ b;
            3'b101: y = a >> b;
            3'b110: y = a << b;
            3'b111: y = ($signed(a)) >>> b;       // signed
        endcase
        if (s == 3'b000) begin
            f[0] = (a == b ? 1'b1 :1'b0);
            f[1] = {a_s, a} < {b_s, b} ? 1'b1 : 1'b0;
            f[2] = (a < b ? 1'b1 :1'b0);
        end
    end
endmodule

计算机组成原理实验/lab1/srcs/alu.vcd
$version Generated by VerilatedVcd $end
$date Fri Mar 18 10:44:52 2022 $end
$timescale 1ps $end

 $scope module TOP $end
  $var wire 32 # a [31:0] $end
  $var wire 32 $ b [31:0] $end
  $var wire  3 ' f [2:0] $end
  $var wire  3 % s [2:0] $end
  $var wire 32 & y [31:0] $end
  $scope module alu $end
   $var wire 32 * WIDTH [31:0] $end
   $var wire 32 # a [31:0] $end
   $var wire  1 ( a_s $end
   $var wire 32 $ b [31:0] $end
   $var wire  1 ) b_s $end
   $var wire  3 ' f [2:0] $end
   $var wire  3 % s [2:0] $end
   $var wire 32 & y [31:0] $end
  $upscope $end
 $upscope $end
$enddefinitions $end


#0
b01111100000010111011010101000110 #
b01100010001001101011100000000110 $
b000 %
b00011001111001001111110101000000 &
b000 '
1(
1)
b00000000000000000000000000100000 *
#1
b00001100011011011100000110000000 #
b01001001101110010010000000111110 $
b11000010101101001010000101000010 &
b110 '
#2
b01010110000011000011011011101011 #
b01100000101110001011010001111101 $
b11110101010100111000001001101110 &
#3
b00111101110011101001101110000000 #
b01010001000100100100000010001010 $
b11101100101111000101101011110110 &
#4
b00001010011111111011101100011101 #
b01011010101010101010010101111000 $
b10101111110101010001010110100101 &
#5
b01001001101000110011111011011010 #
b00111111000100100011100010000111 $
b00001010100100010000011001010011 &
b000 '
#6
b00101001001011110000101101101101 #
b01100100111000101110010010110111 $
b11000100010011000010011010110110 &
b110 '
#7
b01101000011110011100001000010001 #
b00011101100011011101110110000111 $
b01001010111010111110010010001010 &
b000 '
#8
b00100110101011101111010110110101 #
b01011010011011101000010100010001 $
b11001100010000000111000010100100 &
b110 '
#9
b01010011110001000110010001110011 #
b00011000111110000000100101001110 $
b00111010110011000101101100100101 &
b000 '
#10
b00111000111010100101110101101100 #
b01011101111110101101011000101000 $
b001 %
b10010110111001010011001110010100 &
#11
b01101001110111000000000101010011 #
b01101110101110011001001011110100 $
b11011000100101011001010001000111 &
#12
b00011101100101100001111011100000 #
b01111101000011111101110110111011 $
b10011010101001011111110010011011 &
#13
b01100000011101010111100010110101 #
b00111110010100000100010010010101 $
b10011110110001011011110101001010 &
#14
b00011101001000001101101101011011 #
b00101100001101010000001010100111 $
b01001001010101011101111000000010 &
#15
b00011000001010001111011011010111 #
b01101010001000000001010011000100 $
b10000010010010010000101110011011 &
#16
b01001001011101110111010110111100 #
b01110001111101001010001111000010 $
b10111011011011000001100101111110 &
#17
b01101000101101100011111100100100 #
b01000111000011000111010110001110 $
b10101111110000101011010010110010 &
#18
b00000100100111010110101011011100 #
b00011000010110011001010101111101 $
b00011100111101110000000001011001 &
#19
b01010100000101000110001001101000 #
b01100010110101010010100010011111 $
b10110110111010011000101100000111 &
#20
b01010000011101110110000011011110 #
b01011000111000111101111100000010 $
b010 %
b01010000011000110100000000000010 &
#21
b00011100000001110001110010011110 #
b00111010100100010101110110110101 $
b00011000000000010001110010010100 &
#22
b00111010011001110100110011100100 #
b00111110110000101001010101100101 $
b00111010010000100000010001100100 &
#23
b00110000100010010100000010001011 #
b00010001011010000011000001001000 $
b00010000000010000000000000001000 &
#24
b01101101011100010100001111111110 #
b00010111001111001001000001110110 $
b00000101001100000000000001110110 &
#25
b00001110010010011000000100011010 #
b01110111110010000001111110110011 $
b00000110010010000000000100010010 &
#26
b00000011010100000101000110111010 #
b00000001011000000101100000100101 $
b00000001010000000101000000100000 &
#27
b00010111001101001101110110100010 #
b01001001000011110011010101101010 $
b00000001000001000001010100100010 &
#28
b01000100000110101000011100100000 #
b00011000100110010001100000010011 $
b00000000000110000000000000000000 &
#29
b00111001001001110011100000000100 #
b00011001010010011001101110110111 $
b00011001000000010001100000000100 &
#30
b00111001111100001101011000100101 #
b01000110000111101100100010100100 $
b011 %
b01111111111111101101111010100101 &
#31
b00000000111011101101101101000110 #
b01100100011110101100110011110111 $
b01100100111111101101111111110111 &
#32
b01011010111000111100110011110110 #
b01000100100001111010001001100111 $
b01011110111001111110111011110111 &
#33
b01011010000000000110001101110010 #
b01111100000101000011101000000111 $
b01111110000101000111101101110111 &
#34
b01001100011100010111011101001011 #
b00110100101101010110100101001111 $
b01111100111101010111111101001111 &
#35
b01100001101010100001001011110001 #
b01001011010100101001001101101101 $
b01101011111110101001001111111101 &
#36
b00011111101101111011001100100110 #
b00000101111001100011110111001111 $
b00011111111101111011111111101111 &
#37
b00110111000101100010000101001001 #
b01001100011011010111000000010010 $
b01111111011111110111000101011011 &
#38
b01110111001111000000101010100011 #
b01011011100000010000111000011110 $
b01111111101111010000111010111111 &
#39
b01101010000100110011000110100010 #
b01100110100010110000010100101101 $
b01101110100110110011010110101111 &
#40
b00111011101100110011100010000010 #
b00101110001001000100110010101001 $
b100 %
b00010101100101110111010000101011 &
#41
b01100111011000100110100110110000 #
b01110011000001000101000100100001 $
b00010100011001100011100010010001 &
#42
b00100111101011010001100011011100 #
b00010111011110100011010111101001 $
b00110000110101110010110100110101 &
#43
b00100101011111100101100100101001 #
b00101111000110111100010111011111 $
b00001010011001011001110011110110 &
#44
b01000110101110000111010011010111 #
b00011110000101001111011101111001 $
b01011000101011001000001110101110 &
#45
b01010100001100011101110100110101 #
b01101110110101011000110110001110 $
b00111010111001000101000010111011 &
#46
b01111101000011101010000001000010 #
b01000011100110001100110111000001 $
b00111110100101100110110110000011 &
#47
b00001010010100100111011011000001 #
b00101100000110001101000001111101 $
b00100110010010101010011010111100 &
#48
b01010101001101100111101010000100 #
b01011011101110010100101100111000 $
b00001110100011110011000110111100 &
#49
b00000100011101011010001111010110 #
b01110000011011001100010100101111 $
b01110100000110010110011011111001 &
#50
b01110110011101110101011011001001 #
b00110101011110011110100010000001 $
b101 %
b00000000000000000000000000000000 &
#51
b01101010101100111100010001101111 #
b01100001001010111011110001000010 $
#52
b00011001100101111011001000001111 #
b00101111001110101100111101100110 $
#53
b01101001110000110001101101000111 #
b00111001001101110111011100011101 $
#54
b01101000011001101111100010100000 #
b01001101111100111000110101101111 $
#55
b00100110111101000001011111001110 #
b00111000101111110001111010100100 $
#56
b01010100010010010111101100010011 #
b00111000110000110111011010000110 $
#57
b01100011001101100000011000110101 #
b00000100111000011101101110011100 $
#58
b00110001000101110011011011001110 #
b01110101101000110000110011110001 $
#59
b00011110111100010111001001111110 #
b01001101001101110011010010000011 $
#60
b01010110000011110111110011101110 #
b00100110010100101011001111010010 $
b110 %
#61
b00011010100000100110000011011101 #
b00100110101001000101001111000000 $
#62
b01011100010110100110111111001111 #
b01110101101000101100100011011110 $
#63
b01101110101001000011111100011011 #
b01111111011110010001100111101111 $
#64
b01000010110110100101000101011111 #
b00011011101011001101100100011000 $
#65
b01100001011011001100110000101010 #
b01111111101111011011010010010011 $
#66
b01011010111010100111100011010010 #
b00101110010011101111111000110101 $
#67
b01001100001011111000101010110111 #
b00110010011001010000111111011101 $
#68
b01110111111110000011011010100001 #
b01100010000100011001111111011011 $
#69
b00111000010000011110111010100000 #
b00010101011000111111000011111011 $
#70
b01111101010011011101010011001010 #
b00010111111010101110011000001100 $
b111 %
#71
b00111001011010001010000101011100 #
b00101110110111111100111000010100 $
#72
b01001111101000001001000001110000 #
b00100010010100110100101001001111 $
#73
b01101011000110110101101111100001 #
b01000011100100010101111110010011 $
#74
b00010111011100011100000001100110 #
b00111111111000011100000000000011 $
#75
b01101101011001101001000010000001 #
b00000101111000000101001011000011 $
#76
b01001010111111101001001110010000 #
b01110111110110010101111010100001 $
#77
b01110000101001111110011000111010 #
b00010111110111001110000010011111 $
#78
b00011000010001000000100101110110 #
b01011001111001111100111011101010 $
#79
b01000111001010111100011010100110 #
b01001101111011111001110110001101 $
