计算机组成原理实验/lab1/srcs/fls.v
module fls (input clk,
                input rstn,
                input en,
                input [15: 0] d,
                output reg [15: 0] f);

    reg [15: 0] a;
    reg [15: 0] b;

    parameter S_LOAD_0 = 2'b00;		// 初始状态，等待载入第一个数
    parameter S_LOAD_1 = 2'b01;		// 初始状态，等待载入第二个数
    parameter S_WAIT = 2'b10;       // 等待新的使能信号
    parameter S_ADD  = 2'b11;       // 执行加法

    reg[1:0] curr_state;
    reg[1:0] next_state;

    // 状态机状态转换部分
    always @(posedge clk) begin
        curr_state <= (~rstn)? S_LOAD_0 : next_state;
    end

    // 状态机组合逻辑部分
    always @(*) begin
        case (curr_state)
            S_LOAD_0:
                next_state = en? S_LOAD_1 : S_LOAD_0;
            S_LOAD_1:
                next_state = en? S_WAIT : S_LOAD_1;
            S_WAIT:
                next_state = en? S_ADD : S_WAIT;
            S_ADD:
                next_state = S_WAIT;
        endcase
    end

    // 输出逻辑
    always @(*) begin
        case (curr_state)
            S_LOAD_0 :
                f = 0;
            S_LOAD_1 :
                f = a;
            default:
                f = b;
        endcase
    end

    // 载入逻辑
    always @(posedge clk) begin
        case (curr_state)
            S_LOAD_0:
                a <= d;
            S_LOAD_1:
                b <= d;
            S_ADD: begin
                a <= b;
                b <= a + b;
            end
        endcase
    end

endmodule

计算机组成原理实验/lab1/srcs/fls.vcd
$version Generated by VerilatedVcd $end
$date Fri Mar 18 13:20:44 2022 $end
$timescale 1ps $end

 $scope module TOP $end
  $var wire  1 & clk $end
  $var wire 16 ) d [15:0] $end
  $var wire  1 ( en $end
  $var wire 16 * f [15:0] $end
  $var wire  1 ' rstn $end
  $scope module fls $end
   $var wire  2 / S_ADD [1:0] $end
   $var wire  2 , S_LOAD_0 [1:0] $end
   $var wire  2 - S_LOAD_1 [1:0] $end
   $var wire  2 . S_WAIT [1:0] $end
   $var wire 16 # a [15:0] $end
   $var wire 16 $ b [15:0] $end
   $var wire  1 & clk $end
   $var wire  2 % curr_state [1:0] $end
   $var wire 16 ) d [15:0] $end
   $var wire  1 ( en $end
   $var wire 16 * f [15:0] $end
   $var wire  2 + next_state [1:0] $end
   $var wire  1 ' rstn $end
  $upscope $end
 $upscope $end
$enddefinitions $end


#0
b0000000000000000 #
b0000000000000000 $
b00 %
0&
1'
1(
b0000000000000001 )
b0000000000000000 *
b01 +
b00 ,
b01 -
b10 .
b11 /
#1
b0000000000000001 #
b01 %
1&
b10 +
#2
0&
0(
b01 +
#3
b0000000000000001 $
1&
b0000000000000001 *
#4
0&
#5
b0000000000000010 $
1&
b0000000000000010 )
#6
0&
#7
1&
#8
0&
#9
1&
#10
0&
#11
1&
1(
b10 +
#12
0&
#13
b10 %
1&
0(
#14
0&
#15
1&
b0000000000000010 *
#16
0&
#17
1&
#18
0&
#19
1&
#20
0&
#21
1&
#22
0&
1(
b11 +
#23
b11 %
1&
b10 +
#24
0&
0(
#25
b0000000000000010 #
b0000000000000011 $
b10 %
1&
#26
0&
#27
1&
b0000000000000011 *
#28
0&
#29
1&
#30
0&
#31
1&
#32
0&
#33
1&
1(
b11 +
#34
0&
#35
b11 %
1&
0(
b10 +
#36
0&
#37
b0000000000000011 #
b0000000000000101 $
b10 %
1&
#38
0&
#39
1&
b0000000000000101 *
#40
0&
#41
1&
#42
0&
#43
1&
#44
0&
1(
b11 +
#45
b11 %
1&
b10 +
#46
0&
0(
#47
b0000000000000101 #
b0000000000001000 $
b10 %
1&
#48
0&
#49
1&
b0000000000001000 *
#50
0&
#51
1&
#52
0&
#53
1&
#54
0&
#55
1&
1(
b11 +
#56
0&
#57
b11 %
1&
0(
b10 +
#58
0&
#59
b0000000000001000 #
b0000000000001101 $
b10 %
1&
#60
0&
#61
1&
b0000000000001101 *
#62
0&
#63
1&
#64
0&
#65
1&
#66
0&
1(
b11 +
#67
b11 %
1&
b10 +
#68
0&
0(
#69
b0000000000001101 #
b0000000000010101 $
b10 %
1&
#70
0&
#71
1&
b0000000000010101 *
#72
0&
#73
1&
#74
0&
#75
1&
#76
0&
#77
1&
1(
b11 +
#78
0&
#79
b11 %
1&
0(
b10 +
#80
0&
#81
b0000000000010101 #
b0000000000100010 $
b10 %
1&
#82
0&
#83
1&
b0000000000100010 *
#84
0&
#85
1&
#86
0&
#87
1&
#88
0&
1(
b11 +
#89
b11 %
1&
b10 +
#90
0&
0(
#91
b0000000000100010 #
b0000000000110111 $
b10 %
1&
#92
0&
#93
1&
b0000000000110111 *
#94
0&
#95
1&
#96
0&
#97
1&
#98
0&
#99
1&
1(
b11 +
#100
0&
#101
b11 %
1&
0(
b10 +
#102
0&
#103
b0000000000110111 #
b0000000001011001 $
b10 %
1&
#104
0&
#105
1&
b0000000001011001 *
#106
0&
#107
1&
#108
0&
#109
1&
#110
0&
1(
b11 +
#111
b11 %
1&
b10 +
#112
0&
0(
#113
b0000000001011001 #
b0000000010010000 $
b10 %
1&
#114
0&
#115
1&
b0000000010010000 *
#116
0&
#117
1&
#118
0&
#119
1&
#120
0&
#121
1&
1(
b11 +
#122
0&
#123
b11 %
1&
0(
b10 +
#124
0&
#125
b0000000010010000 #
b0000000011101001 $
b10 %
1&
#126
0&
#127
1&
b0000000011101001 *
#128
0&
#129
1&
#130
0&
#131
1&
#132
0&
1(
b11 +
#133
b11 %
1&
b10 +
#134
0&
0(
#135
b0000000011101001 #
b0000000101111001 $
b10 %
1&
#136
0&
#137
1&
b0000000101111001 *
#138
0&
#139
1&
#140
0&
#141
1&
#142
0&
#143
1&
1(
b11 +
#144
0&
#145
b11 %
1&
0(
b10 +
#146
0&
#147
b0000000101111001 #
b0000001001100010 $
b10 %
1&
#148
0&
#149
1&
b0000001001100010 *
#150
0&
#151
1&
#152
0&
#153
1&
#154
0&
1(
b11 +
#155
b11 %
1&
b10 +
#156
0&
0(
#157
b0000001001100010 #
b0000001111011011 $
b10 %
1&
#158
0&
#159
1&
b0000001111011011 *
#160
0&
#161
1&
#162
0&
#163
1&
#164
0&
#165
1&
1(
b11 +
#166
0&
#167
b11 %
1&
0(
b10 +
#168
0&
#169
b0000001111011011 #
b0000011000111101 $
b10 %
1&
#170
0&
#171
1&
b0000011000111101 *
#172
0&
#173
1&
#174
0&
#175
1&
#176
0&
1(
b11 +
#177
b11 %
1&
b10 +
#178
0&
0(
#179
b0000011000111101 #
b0000101000011000 $
b10 %
1&
#180
0&
#181
1&
b0000101000011000 *
#182
0&
#183
1&
#184
0&
#185
1&
#186
0&
#187
1&
1(
b11 +
#188
0&
#189
b11 %
1&
0(
b10 +
#190
0&
#191
b0000101000011000 #
b0001000001010101 $
b10 %
1&
#192
0&
#193
1&
b0001000001010101 *
#194
0&
#195
1&
#196
0&
#197
1&
#198
0&
1(
b11 +
#199
b11 %
1&
b10 +
#200
0&
0(
#201
b0001000001010101 #
b0001101001101101 $
b10 %
1&
#202
0&
#203
1&
b0001101001101101 *
#204
0&
#205
1&
#206
0&
#207
1&
#208
0&
#209
1&
1(
b11 +
#210
0&
#211
b11 %
1&
0(
b10 +
#212
0&
#213
b0001101001101101 #
b0010101011000010 $
b10 %
1&
#214
0&
#215
1&
b0010101011000010 *
#216
0&
#217
1&
#218
0&
#219
1&
#220
0&
1(
b11 +
#221
b11 %
1&
b10 +
#222
0&
0(
#223
b0010101011000010 #
b0100010100101111 $
b10 %
1&
#224
0&
#225
1&
b0100010100101111 *
#226
0&
#227
1&
#228
0&
#229
1&
#230
0&
#231
1&
1(
b11 +
#232
0&
#233
b11 %
1&
0(
b10 +
#234
0&
#235
b0100010100101111 #
b0110111111110001 $
b10 %
1&
#236
0&
#237
1&
b0110111111110001 *
#238
0&
#239
1&
#240
0&
#241
1&
#242
0&
1(
b11 +
#243
b11 %
1&
b10 +
#244
0&
0(
#245
b0110111111110001 #
b1011010100100000 $
b10 %
1&
#246
0&
#247
1&
b1011010100100000 *
#248
0&
#249
1&
#250
0&
#251
1&
#252
0&
#253
1&
1(
b11 +
#254
0&
#255
b11 %
1&
0(
b10 +
#256
0&
#257
b1011010100100000 #
b0010010100010001 $
b10 %
1&
#258
0&
#259
1&
b0010010100010001 *
#260
0&
#261
1&
#262
0&
#263
1&
#264
0&
1(
b11 +
#265
b11 %
1&
b10 +
#266
0&
0(
#267
b0010010100010001 #
b1101101000110001 $
b10 %
1&
#268
0&
#269
1&
b1101101000110001 *
#270
0&
#271
1&
#272
0&
#273
1&
#274
0&
#275
1&
1(
b11 +
#276
0&
#277
b11 %
1&
0(
b10 +
#278
0&
#279
b1101101000110001 #
b1111111101000010 $
b10 %
1&
#280
0&
#281
1&
b1111111101000010 *
#282
0&
#283
1&
#284
0&
#285
1&
#286
0&
1(
b11 +
#287
b11 %
1&
b10 +
#288
0&
0(
#289
b1111111101000010 #
b1101100101110011 $
b10 %
1&
#290
0&
#291
1&
b1101100101110011 *
#292
0&
#293
1&
#294
0&
#295
1&
#296
0&
#297
1&
1(
b11 +
#298
0&
#299
b11 %
1&
0(
b10 +
#300
0&
#301
b1101100101110011 #
b1101100010110101 $
b10 %
1&
#302
0&
#303
1&
b1101100010110101 *
#304
0&
#305
1&
#306
0&
#307
1&
#308
0&
1(
b11 +
#309
b11 %
1&
b10 +
#310
0&
0(
#311
b1101100010110101 #
b1011001000101000 $
b10 %
1&
#312
0&
#313
1&
b1011001000101000 *
#314
0&
#315
1&
#316
0&
#317
1&
#318
0&
#319
1&
1(
b11 +
#320
0&
#321
b11 %
1&
0(
b10 +
#322
0&
#323
b1011001000101000 #
b1000101011011101 $
b10 %
1&
#324
0&
#325
1&
b1000101011011101 *
#326
0&
#327
1&
#328
0&
#329
1&
#330
0&
1(
b11 +
#331
b11 %
1&
b10 +
#332
0&
0(
#333
b1000101011011101 #
b0011110100000101 $
b10 %
1&
#334
0&
#335
1&
b0011110100000101 *
#336
0&
#337
1&
#338
0&
#339
1&
#340
0&
#341
1&
1(
b11 +
#342
0&
#343
b11 %
1&
0(
b10 +
#344
0&
#345
b0011110100000101 #
b1100011111100010 $
b10 %
1&
#346
0&
#347
1&
b1100011111100010 *
#348
0&
#349
1&
#350
0&
#351
1&
#352
0&
1(
b11 +
#353
b11 %
1&
b10 +
#354
0&
0(
#355
b1100011111100010 #
b0000010011100111 $
b10 %
1&
#356
0&
#357
1&
b0000010011100111 *
#358
0&
#359
1&
#360
0&
#361
1&
#362
0&
#363
1&
1(
b11 +
#364
0&
#365
b11 %
1&
0(
b10 +
#366
0&
#367
b0000010011100111 #
b1100110011001001 $
b10 %
1&
#368
0&
#369
1&
b1100110011001001 *
#370
0&
#371
1&
#372
0&
#373
1&
#374
0&
1(
b11 +
#375
b11 %
1&
b10 +
#376
0&
0(
#377
b1100110011001001 #
b1101000110110000 $
b10 %
1&
#378
0&
#379
1&
b1101000110110000 *
#380
0&
#381
1&
#382
0&
#383
1&
#384
0&
#385
1&
1(
b11 +
#386
0&
#387
b11 %
1&
0(
b10 +
#388
0&
#389
b1101000110110000 #
b1001111001111001 $
b10 %
1&
#390
0&
#391
1&
b1001111001111001 *
#392
0&
#393
1&
#394
0&
#395
1&
#396
0&
1(
b11 +
#397
b11 %
1&
b10 +
#398
0&
0(
#399
b1001111001111001 #
b0111000000101001 $
b10 %
1&
#400
0&
#401
1&
b0111000000101001 *
#402
0&
#403
1&
#404
0&
#405
1&
#406
0&
#407
1&
1(
b11 +
#408
0&
#409
b11 %
1&
0(
b10 +
#410
0&
#411
b0111000000101001 #
b0000111010100010 $
b10 %
1&
#412
0&
#413
1&
b0000111010100010 *
#414
0&
#415
1&
#416
0&
#417
1&
#418
0&
1(
b11 +
#419
b11 %
1&
b10 +
#420
0&
0(
#421
b0000111010100010 #
b0111111011001011 $
b10 %
1&
#422
0&
#423
1&
b0111111011001011 *
#424
0&
#425
1&
#426
0&
#427
1&
#428
0&
#429
1&
1(
b11 +
#430
0&
#431
b11 %
1&
0(
b10 +
#432
0&
#433
b0111111011001011 #
b1000110101101101 $
b10 %
1&
#434
0&
#435
1&
b1000110101101101 *
#436
0&
#437
1&
#438
0&
#439
1&
#440
0&
1(
b11 +
#441
b11 %
1&
b10 +
#442
0&
0(
#443
b1000110101101101 #
b0000110000111000 $
b10 %
1&
#444
0&
#445
1&
b0000110000111000 *
#446
0&
#447
1&
#448
0&
#449
1&
#450
0&
#451
1&
1(
b11 +
#452
0&
#453
b11 %
1&
0(
b10 +
#454
0&
#455
b0000110000111000 #
b1001100110100101 $
b10 %
1&
#456
0&
#457
1&
b1001100110100101 *
#458
0&
#459
1&
#460
0&
#461
1&
#462
0&
1(
b11 +
#463
b11 %
1&
b10 +
#464
0&
0(
#465
b1001100110100101 #
b1010010111011101 $
b10 %
1&
#466
0&
#467
1&
b1010010111011101 *
#468
0&
#469
1&
#470
0&
#471
1&
#472
0&
#473
1&
1(
b11 +
#474
0&
#475
b11 %
1&
0(
b10 +
#476
0&
#477
b1010010111011101 #
b0011111110000010 $
b10 %
1&
#478
0&
#479
1&
b0011111110000010 *
#480
0&
#481
1&
#482
0&
#483
1&
#484
0&
1(
b11 +
#485
b11 %
1&
b10 +
#486
0&
0(
#487
b0011111110000010 #
b1110010101011111 $
b10 %
1&
#488
0&
#489
1&
b1110010101011111 *
#490
0&
#491
1&
#492
0&
#493
1&
#494
0&
#495
1&
1(
b11 +
#496
0&
#497
b11 %
1&
0(
b10 +
#498
0&
#499
b1110010101011111 #
b0010010011100001 $
b10 %
1&
#500
0&
#501
1&
b0010010011100001 *
#502
0&
#503
1&
#504
0&
#505
1&
#506
0&
1(
b11 +
#507
b11 %
1&
b10 +
#508
0&
0(
#509
b0010010011100001 #
b0000101001000000 $
b10 %
1&
#510
0&
#511
1&
b0000101001000000 *
#512
0&
#513
b00 %
1&
0'
b00 +
#514
0&
1'
#515
b0000000000000010 #
1&
b0000000000000000 *
#516
0&
#517
1&
1(
b01 +
#518
0&
#519
b01 %
1&
0(
#520
0&
#521
b0000000000000010 $
1&
b0000000000000010 *
#522
0&
#523
1&
#524
0&
#525
1&
#526
0&
#527
1&
#528
0&
1(
b10 +
#529
b10 %
1&
b11 +
#530
0&
0(
b10 +
#531
1&
#532
0&
#533
1&
#534
0&
#535
1&
#536
0&
#537
1&
#538
0&
#539
1&
1(
b11 +
#540
0&
#541
b11 %
1&
0(
b10 +
#542
0&
#543
b0000000000000100 $
b10 %
1&
#544
0&
#545
1&
b0000000000000100 *
#546
0&
#547
1&
#548
0&
#549
1&
#550
0&
1(
b11 +
#551
b11 %
1&
b10 +
#552
0&
0(
#553
b0000000000000100 #
b0000000000000110 $
b10 %
1&
#554
0&
#555
1&
b0000000000000110 *
#556
0&
#557
1&
#558
0&
#559
1&
#560
0&
#561
1&
1(
b11 +
#562
0&
#563
b11 %
1&
0(
b10 +
#564
0&
#565
b0000000000000110 #
b0000000000001010 $
b10 %
1&
#566
0&
#567
1&
b0000000000001010 *
#568
0&
#569
1&
#570
0&
#571
1&
#572
0&
1(
b11 +
#573
b11 %
1&
b10 +
#574
0&
0(
#575
b0000000000001010 #
b0000000000010000 $
b10 %
1&
#576
0&
#577
1&
b0000000000010000 *
#578
0&
#579
1&
#580
0&
#581
1&
#582
0&
#583
1&
1(
b11 +
#584
0&
#585
b11 %
1&
0(
b10 +
#586
0&
#587
b0000000000010000 #
b0000000000011010 $
b10 %
1&
#588
0&
#589
1&
b0000000000011010 *
#590
0&
#591
1&
#592
0&
#593
1&
#594
0&
1(
b11 +
#595
b11 %
1&
b10 +
#596
0&
0(
#597
b0000000000011010 #
b0000000000101010 $
b10 %
1&
#598
0&
#599
1&
b0000000000101010 *
#600
0&
#601
1&
#602
0&
#603
1&
#604
0&
#605
1&
1(
b11 +
#606
0&
#607
b11 %
1&
0(
b10 +
#608
0&
#609
b0000000000101010 #
b0000000001000100 $
b10 %
1&
#610
0&
#611
1&
b0000000001000100 *
#612
0&
#613
1&
#614
0&
#615
1&
#616
0&
1(
b11 +
#617
b11 %
1&
b10 +
#618
0&
0(
#619
b0000000001000100 #
b0000000001101110 $
b10 %
1&
#620
0&
#621
1&
b0000000001101110 *
#622
0&
#623
1&
#624
0&
#625
1&
#626
0&
#627
1&
1(
b11 +
#628
0&
#629
b11 %
1&
0(
b10 +
#630
0&
#631
b0000000001101110 #
b0000000010110010 $
b10 %
1&
#632
0&
#633
1&
b0000000010110010 *
#634
0&
#635
1&
#636
0&
#637
1&
#638
0&
1(
b11 +
#639
b11 %
1&
b10 +
#640
0&
0(
#641
b0000000010110010 #
b0000000100100000 $
b10 %
1&
#642
0&
#643
1&
b0000000100100000 *
#644
0&
#645
1&
#646
0&
#647
1&
#648
0&
#649
1&
1(
b11 +
#650
0&
#651
b11 %
1&
0(
b10 +
#652
0&
#653
b0000000100100000 #
b0000000111010010 $
b10 %
1&
#654
0&
#655
1&
b0000000111010010 *
#656
0&
#657
1&
#658
0&
#659
1&
#660
0&
1(
b11 +
#661
b11 %
1&
b10 +
#662
0&
0(
#663
b0000000111010010 #
b0000001011110010 $
b10 %
1&
#664
0&
#665
1&
b0000001011110010 *
#666
0&
#667
1&
#668
0&
#669
1&
#670
0&
#671
1&
1(
b11 +
#672
0&
#673
b11 %
1&
0(
b10 +
#674
0&
#675
b0000001011110010 #
b0000010011000100 $
b10 %
1&
#676
0&
#677
1&
b0000010011000100 *
#678
0&
#679
1&
#680
0&
#681
1&
#682
0&
1(
b11 +
#683
b11 %
1&
b10 +
#684
0&
0(
#685
b0000010011000100 #
b0000011110110110 $
b10 %
1&
#686
0&
#687
1&
b0000011110110110 *
#688
0&
#689
1&
#690
0&
#691
1&
#692
0&
#693
1&
1(
b11 +
#694
0&
#695
b11 %
1&
0(
b10 +
#696
0&
#697
b0000011110110110 #
b0000110001111010 $
b10 %
1&
#698
0&
#699
1&
b0000110001111010 *
#700
0&
#701
1&
#702
0&
#703
1&
#704
0&
1(
b11 +
#705
b11 %
1&
b10 +
#706
0&
0(
#707
b0000110001111010 #
b0001010000110000 $
b10 %
1&
#708
0&
#709
1&
b0001010000110000 *
#710
0&
#711
1&
#712
0&
#713
1&
#714
0&
#715
1&
1(
b11 +
#716
0&
#717
b11 %
1&
0(
b10 +
#718
0&
#719
b0001010000110000 #
b0010000010101010 $
b10 %
1&
#720
0&
#721
1&
b0010000010101010 *
#722
0&
#723
1&
#724
0&
#725
1&
#726
0&
1(
b11 +
#727
b11 %
1&
b10 +
#728
0&
0(
#729
b0010000010101010 #
b0011010011011010 $
b10 %
1&
#730
0&
#731
1&
b0011010011011010 *
#732
0&
#733
1&
#734
0&
#735
1&
#736
0&
#737
1&
1(
b11 +
#738
0&
#739
b11 %
1&
0(
b10 +
#740
0&
#741
b0011010011011010 #
b0101010110000100 $
b10 %
1&
#742
0&
#743
1&
b0101010110000100 *
#744
0&
#745
1&
#746
0&
#747
1&
#748
0&
1(
b11 +
#749
b11 %
1&
b10 +
#750
0&
0(
#751
b0101010110000100 #
b1000101001011110 $
b10 %
1&
#752
0&
#753
1&
b1000101001011110 *
#754
0&
#755
1&
#756
0&
#757
1&
#758
0&
#759
1&
1(
b11 +
#760
0&
#761
b11 %
1&
0(
b10 +
#762
0&
#763
b1000101001011110 #
b1101111111100010 $
b10 %
1&
#764
0&
#765
1&
b1101111111100010 *
#766
0&
#767
1&
#768
0&
#769
1&
#770
0&
1(
b11 +
#771
b11 %
1&
b10 +
#772
0&
0(
#773
b1101111111100010 #
b0110101001000000 $
b10 %
1&
#774
0&
#775
1&
b0110101001000000 *
#776
0&
#777
1&
#778
0&
#779
1&
#780
0&
#781
1&
1(
b11 +
#782
0&
#783
b11 %
1&
0(
b10 +
#784
0&
#785
b0110101001000000 #
b0100101000100010 $
b10 %
1&
#786
0&
#787
1&
b0100101000100010 *
#788
0&
#789
1&
#790
0&
#791
1&
#792
0&
1(
b11 +
#793
b11 %
1&
b10 +
#794
0&
0(
#795
b0100101000100010 #
b1011010001100010 $
b10 %
1&
#796
0&
#797
1&
b1011010001100010 *
#798
0&
#799
1&
#800
0&
#801
1&
#802
0&
#803
1&
1(
b11 +
#804
0&
#805
b11 %
1&
0(
b10 +
#806
0&
#807
b1011010001100010 #
b1111111010000100 $
b10 %
1&
#808
0&
#809
1&
b1111111010000100 *
#810
0&
#811
1&
#812
0&
#813
1&
#814
0&
1(
b11 +
#815
b11 %
1&
b10 +
#816
0&
0(
#817
b1111111010000100 #
b1011001011100110 $
b10 %
1&
#818
0&
#819
1&
b1011001011100110 *
#820
0&
#821
1&
#822
0&
#823
1&
#824
0&
#825
1&
1(
b11 +
#826
0&
#827
b11 %
1&
0(
b10 +
#828
0&
#829
b1011001011100110 #
b1011000101101010 $
b10 %
1&
#830
0&
#831
1&
b1011000101101010 *
#832
0&
#833
1&
#834
0&
#835
1&
#836
0&
1(
b11 +
#837
b11 %
1&
b10 +
#838
0&
0(
#839
b1011000101101010 #
b0110010001010000 $
b10 %
1&
#840
0&
#841
1&
b0110010001010000 *
#842
0&
#843
1&
#844
0&
#845
1&
#846
0&
#847
1&
1(
b11 +
#848
0&
#849
b11 %
1&
0(
b10 +
#850
0&
#851
b0110010001010000 #
b0001010110111010 $
b10 %
1&
#852
0&
#853
1&
b0001010110111010 *
#854
0&
#855
1&
#856
0&
#857
1&
#858
0&
1(
b11 +
#859
b11 %
1&
b10 +
#860
0&
0(
#861
b0001010110111010 #
b0111101000001010 $
b10 %
1&
#862
0&
#863
1&
b0111101000001010 *
#864
0&
#865
1&
#866
0&
#867
1&
#868
0&
#869
1&
1(
b11 +
#870
0&
#871
b11 %
1&
0(
b10 +
#872
0&
#873
b0111101000001010 #
b1000111111000100 $
b10 %
1&
#874
0&
#875
1&
b1000111111000100 *
#876
0&
#877
1&
#878
0&
#879
1&
#880
0&
1(
b11 +
#881
b11 %
1&
b10 +
#882
0&
0(
#883
b1000111111000100 #
b0000100111001110 $
b10 %
1&
#884
0&
#885
1&
b0000100111001110 *
#886
0&
#887
1&
#888
0&
#889
1&
#890
0&
#891
1&
1(
b11 +
#892
0&
#893
b11 %
1&
0(
b10 +
#894
0&
#895
b0000100111001110 #
b1001100110010010 $
b10 %
1&
#896
0&
#897
1&
b1001100110010010 *
#898
0&
#899
1&
#900
0&
#901
1&
#902
0&
1(
b11 +
#903
b11 %
1&
b10 +
#904
0&
0(
#905
b1001100110010010 #
b1010001101100000 $
b10 %
1&
#906
0&
#907
1&
b1010001101100000 *
#908
0&
#909
1&
#910
0&
#911
1&
#912
0&
#913
1&
1(
b11 +
#914
0&
#915
b11 %
1&
0(
b10 +
#916
0&
#917
b1010001101100000 #
b0011110011110010 $
b10 %
1&
#918
0&
#919
1&
b0011110011110010 *
#920
0&
#921
1&
#922
0&
#923
1&
#924
0&
1(
b11 +
#925
b11 %
1&
b10 +
#926
0&
0(
#927
b0011110011110010 #
b1110000001010010 $
b10 %
1&
#928
0&
#929
1&
b1110000001010010 *
#930
0&
#931
1&
#932
0&
#933
1&
#934
0&
#935
1&
1(
b11 +
#936
0&
#937
b11 %
1&
0(
b10 +
#938
0&
#939
b1110000001010010 #
b0001110101000100 $
b10 %
1&
#940
0&
#941
1&
b0001110101000100 *
#942
0&
#943
1&
#944
0&
#945
1&
#946
0&
1(
b11 +
#947
b11 %
1&
b10 +
#948
0&
0(
#949
b0001110101000100 #
b1111110110010110 $
b10 %
1&
#950
0&
#951
1&
b1111110110010110 *
#952
0&
#953
1&
#954
0&
#955
1&
#956
0&
#957
1&
1(
b11 +
#958
0&
#959
b11 %
1&
0(
b10 +
#960
0&
#961
b1111110110010110 #
b0001101011011010 $
b10 %
1&
#962
0&
#963
1&
b0001101011011010 *
#964
0&
#965
1&
#966
0&
#967
1&
#968
0&
1(
b11 +
#969
b11 %
1&
b10 +
#970
0&
0(
#971
b0001101011011010 #
b0001100001110000 $
b10 %
1&
#972
0&
#973
1&
b0001100001110000 *
#974
0&
#975
1&
#976
0&
#977
1&
#978
0&
#979
1&
1(
b11 +
#980
0&
#981
b11 %
1&
0(
b10 +
#982
0&
#983
b0001100001110000 #
b0011001101001010 $
b10 %
1&
#984
0&
#985
1&
b0011001101001010 *
#986
0&
#987
1&
#988
0&
#989
1&
#990
0&
1(
b11 +
#991
b11 %
1&
b10 +
#992
0&
0(
#993
b0011001101001010 #
b0100101110111010 $
b10 %
1&
#994
0&
#995
1&
b0100101110111010 *
#996
0&
#997
1&
#998
0&
#999
1&
#1000
0&
#1001
1&
1(
b11 +
#1002
0&
#1003
b11 %
1&
0(
b10 +
#1004
0&
#1005
b0100101110111010 #
b0111111100000100 $
b10 %
1&
#1006
0&
#1007
1&
b0111111100000100 *
#1008
0&
#1009
1&
#1010
0&
#1011
1&
#1012
0&
1(
b11 +
#1013
b11 %
1&
b10 +
#1014
0&
0(
#1015
b0111111100000100 #
b1100101010111110 $
b10 %
1&
#1016
0&
#1017
1&
b1100101010111110 *
#1018
0&
#1019
1&
#1020
0&
#1021
1&
#1022
0&
#1023
1&
1(
b11 +
