计算机组成原理实验/lab1/srcs/fls.v
module fls (input clk,
                input rstn,
                input en,
                input [15: 0] d,
                output reg [15: 0] f);

    reg [15: 0] a;
    reg [15: 0] b;

    parameter S_LOAD_0 = 2'b00;		// 初始状态，等待载入第一个数
    parameter S_LOAD_1 = 2'b01;		// 初始状态，等待载入第二个数
    parameter S_WAIT = 2'b10;       // 等待新的使能信号
    parameter S_ADD  = 2'b11;       // 执行加法

    reg[1:0] curr_state;
    reg[1:0] next_state;

    // 状态机状态转换部分
    always @(posedge clk) begin
        curr_state <= (~rstn)? S_LOAD_0 : next_state;
    end

    // 状态机组合逻辑部分
    always @(*) begin
        case (curr_state)
            S_LOAD_0:
                next_state = en? S_LOAD_1 : S_LOAD_0;
            S_LOAD_1:
                next_state = en? S_WAIT : S_LOAD_1;
            S_WAIT:
                next_state = en? S_ADD : S_WAIT;
            S_ADD:
                next_state = S_WAIT;
        endcase
    end

    // 输出逻辑
    always @(*) begin
        case (curr_state)
            S_LOAD_0 :
                f = 0;
            S_LOAD_1 :
                f = a;
            default:
                f = b;
        endcase
    end

    // 载入逻辑
    always @(posedge clk) begin
        case (curr_state)
            S_LOAD_0:
                a <= d;
            S_LOAD_1:
                b <= d;
            S_ADD: begin
                a <= b;
                b <= a + b;
            end
        endcase
    end

endmodule

计算机组成原理实验/lab1/srcs/fls.vcd
$version Generated by VerilatedVcd $end
$date Sun Mar 20 08:45:18 2022
 $end
$timescale   1ns $end

 $scope module TOP $end
  $var wire  1 ' clk $end
  $var wire 16 * d [15:0] $end
  $var wire  1 ) en $end
  $var wire 16 + f [15:0] $end
  $var wire  1 ( rstn $end
  $scope module fls $end
   $var wire  2 / S_ADD [1:0] $end
   $var wire  2 , S_LOAD_0 [1:0] $end
   $var wire  2 - S_LOAD_1 [1:0] $end
   $var wire  2 . S_WAIT [1:0] $end
   $var wire 16 $ a [15:0] $end
   $var wire 16 % b [15:0] $end
   $var wire  1 ' clk $end
   $var wire  2 & curr_state [1:0] $end
   $var wire 16 * d [15:0] $end
   $var wire  1 ) en $end
   $var wire 16 + f [15:0] $end
   $var wire  2 # next_state [1:0] $end
   $var wire  1 ( rstn $end
  $upscope $end
 $upscope $end
$enddefinitions $end


#0
b01 #
b0000000000000000 $
b0000000000000000 %
b00 &
0'
1(
1)
b0000000000000001 *
b0000000000000000 +
b00 ,
b01 -
b10 .
b11 /
#1
b10 #
b0000000000000001 $
b01 &
1'
b0000000000000001 +
#2
b01 #
0'
0)
#3
b0000000000000001 %
1'
#4
0'
#5
b0000000000000010 %
1'
b0000000000000010 *
#6
0'
#7
1'
#8
0'
#9
1'
#10
0'
#11
b10 #
1'
1)
#12
0'
#13
b10 &
1'
0)
b0000000000000010 +
#14
0'
#15
1'
#16
0'
#17
1'
#18
0'
#19
1'
#20
0'
#21
1'
#22
b11 #
0'
1)
#23
b10 #
b11 &
1'
#24
0'
0)
#25
b0000000000000010 $
b0000000000000011 %
b10 &
1'
b0000000000000011 +
#26
0'
#27
1'
#28
0'
#29
1'
#30
0'
#31
1'
#32
0'
#33
b11 #
1'
1)
#34
0'
#35
b10 #
b11 &
1'
0)
#36
0'
#37
b0000000000000011 $
b0000000000000101 %
b10 &
1'
b0000000000000101 +
#38
0'
#39
1'
#40
0'
#41
1'
#42
0'
#43
1'
#44
b11 #
0'
1)
#45
b10 #
b11 &
1'
#46
0'
0)
#47
b0000000000000101 $
b0000000000001000 %
b10 &
1'
b0000000000001000 +
#48
0'
#49
1'
#50
0'
#51
1'
#52
0'
#53
1'
#54
0'
#55
b11 #
1'
1)
#56
0'
#57
b10 #
b11 &
1'
0)
#58
0'
#59
b0000000000001000 $
b0000000000001101 %
b10 &
1'
b0000000000001101 +
#60
0'
#61
1'
#62
0'
#63
1'
#64
0'
#65
1'
#66
b11 #
0'
1)
#67
b10 #
b11 &
1'
#68
0'
0)
#69
b0000000000001101 $
b0000000000010101 %
b10 &
1'
b0000000000010101 +
#70
0'
#71
1'
#72
0'
#73
1'
#74
0'
#75
1'
#76
0'
#77
b11 #
1'
1)
#78
0'
#79
b10 #
b11 &
1'
0)
#80
0'
#81
b0000000000010101 $
b0000000000100010 %
b10 &
1'
b0000000000100010 +
#82
0'
#83
1'
#84
0'
#85
1'
#86
0'
#87
1'
#88
b11 #
0'
1)
#89
b10 #
b11 &
1'
#90
0'
0)
#91
b0000000000100010 $
b0000000000110111 %
b10 &
1'
b0000000000110111 +
#92
0'
#93
1'
#94
0'
#95
1'
#96
0'
#97
1'
#98
0'
#99
b11 #
1'
1)
#100
0'
#101
b10 #
b11 &
1'
0)
#102
0'
#103
b0000000000110111 $
b0000000001011001 %
b10 &
1'
b0000000001011001 +
#104
0'
#105
1'
#106
0'
#107
1'
#108
0'
#109
1'
#110
b11 #
0'
1)
#111
b10 #
b11 &
1'
#112
0'
0)
#113
b0000000001011001 $
b0000000010010000 %
b10 &
1'
b0000000010010000 +
#114
0'
#115
1'
#116
0'
#117
1'
#118
0'
#119
1'
#120
0'
#121
b11 #
1'
1)
#122
0'
#123
b10 #
b11 &
1'
0)
#124
0'
#125
b0000000010010000 $
b0000000011101001 %
b10 &
1'
b0000000011101001 +
#126
0'
#127
1'
#128
0'
#129
1'
#130
0'
#131
1'
#132
b11 #
0'
1)
#133
b10 #
b11 &
1'
#134
0'
0)
#135
b0000000011101001 $
b0000000101111001 %
b10 &
1'
b0000000101111001 +
#136
0'
#137
1'
#138
0'
#139
1'
#140
0'
#141
1'
#142
0'
#143
b11 #
1'
1)
#144
0'
#145
b10 #
b11 &
1'
0)
#146
0'
#147
b0000000101111001 $
b0000001001100010 %
b10 &
1'
b0000001001100010 +
#148
0'
#149
1'
#150
0'
#151
1'
#152
0'
#153
1'
#154
b11 #
0'
1)
#155
b10 #
b11 &
1'
#156
0'
0)
#157
b0000001001100010 $
b0000001111011011 %
b10 &
1'
b0000001111011011 +
#158
0'
#159
1'
#160
0'
#161
1'
#162
0'
#163
1'
#164
0'
#165
b11 #
1'
1)
#166
0'
#167
b10 #
b11 &
1'
0)
#168
0'
#169
b0000001111011011 $
b0000011000111101 %
b10 &
1'
b0000011000111101 +
#170
0'
#171
1'
#172
0'
#173
1'
#174
0'
#175
1'
#176
b11 #
0'
1)
#177
b10 #
b11 &
1'
#178
0'
0)
#179
b0000011000111101 $
b0000101000011000 %
b10 &
1'
b0000101000011000 +
#180
0'
#181
1'
#182
0'
#183
1'
#184
0'
#185
1'
#186
0'
#187
b11 #
1'
1)
#188
0'
#189
b10 #
b11 &
1'
0)
#190
0'
#191
b0000101000011000 $
b0001000001010101 %
b10 &
1'
b0001000001010101 +
#192
0'
#193
1'
#194
0'
#195
1'
#196
0'
#197
1'
#198
b11 #
0'
1)
#199
b10 #
b11 &
1'
#200
0'
0)
#201
b0001000001010101 $
b0001101001101101 %
b10 &
1'
b0001101001101101 +
#202
0'
#203
1'
#204
0'
#205
1'
#206
0'
#207
1'
#208
0'
#209
b11 #
1'
1)
#210
0'
#211
b10 #
b11 &
1'
0)
#212
0'
#213
b0001101001101101 $
b0010101011000010 %
b10 &
1'
b0010101011000010 +
#214
0'
#215
1'
#216
0'
#217
1'
#218
0'
#219
1'
#220
b11 #
0'
1)
#221
b10 #
b11 &
1'
#222
0'
0)
#223
b0010101011000010 $
b0100010100101111 %
b10 &
1'
b0100010100101111 +
#224
0'
#225
1'
#226
0'
#227
1'
#228
0'
#229
1'
#230
0'
#231
b11 #
1'
1)
#232
0'
#233
b10 #
b11 &
1'
0)
#234
0'
#235
b0100010100101111 $
b0110111111110001 %
b10 &
1'
b0110111111110001 +
#236
0'
#237
1'
#238
0'
#239
1'
#240
0'
#241
1'
#242
b11 #
0'
1)
#243
b10 #
b11 &
1'
#244
0'
0)
#245
b0110111111110001 $
b1011010100100000 %
b10 &
1'
b1011010100100000 +
#246
0'
#247
1'
#248
0'
#249
1'
#250
0'
#251
1'
#252
0'
#253
b11 #
1'
1)
#254
0'
#255
b10 #
b11 &
1'
0)
#256
0'
#257
b1011010100100000 $
b0010010100010001 %
b10 &
1'
b0010010100010001 +
#258
0'
#259
1'
#260
0'
#261
1'
#262
0'
#263
1'
#264
b11 #
0'
1)
#265
b10 #
b11 &
1'
#266
0'
0)
#267
b0010010100010001 $
b1101101000110001 %
b10 &
1'
b1101101000110001 +
#268
0'
#269
1'
#270
0'
#271
1'
#272
0'
#273
1'
#274
0'
#275
b11 #
1'
1)
#276
0'
#277
b10 #
b11 &
1'
0)
#278
0'
#279
b1101101000110001 $
b1111111101000010 %
b10 &
1'
b1111111101000010 +
#280
0'
#281
1'
#282
0'
#283
1'
#284
0'
#285
1'
#286
b11 #
0'
1)
#287
b10 #
b11 &
1'
#288
0'
0)
#289
b1111111101000010 $
b1101100101110011 %
b10 &
1'
b1101100101110011 +
#290
0'
#291
1'
#292
0'
#293
1'
#294
0'
#295
1'
#296
0'
#297
b11 #
1'
1)
#298
0'
#299
b10 #
b11 &
1'
0)
#300
0'
#301
b1101100101110011 $
b1101100010110101 %
b10 &
1'
b1101100010110101 +
#302
0'
#303
1'
#304
0'
#305
1'
#306
0'
#307
1'
#308
b11 #
0'
1)
#309
b10 #
b11 &
1'
#310
0'
0)
#311
b1101100010110101 $
b1011001000101000 %
b10 &
1'
b1011001000101000 +
#312
0'
#313
1'
#314
0'
#315
1'
#316
0'
#317
1'
#318
0'
#319
b11 #
1'
1)
#320
0'
#321
b10 #
b11 &
1'
0)
#322
0'
#323
b1011001000101000 $
b1000101011011101 %
b10 &
1'
b1000101011011101 +
#324
0'
#325
1'
#326
0'
#327
1'
#328
0'
#329
1'
#330
b11 #
0'
1)
#331
b10 #
b11 &
1'
#332
0'
0)
#333
b1000101011011101 $
b0011110100000101 %
b10 &
1'
b0011110100000101 +
#334
0'
#335
1'
#336
0'
#337
1'
#338
0'
#339
1'
#340
0'
#341
b11 #
1'
1)
#342
0'
#343
b10 #
b11 &
1'
0)
#344
0'
#345
b0011110100000101 $
b1100011111100010 %
b10 &
1'
b1100011111100010 +
#346
0'
#347
1'
#348
0'
#349
1'
#350
0'
#351
1'
#352
b11 #
0'
1)
#353
b10 #
b11 &
1'
#354
0'
0)
#355
b1100011111100010 $
b0000010011100111 %
b10 &
1'
b0000010011100111 +
#356
0'
#357
1'
#358
0'
#359
1'
#360
0'
#361
1'
#362
0'
#363
b11 #
1'
1)
#364
0'
#365
b10 #
b11 &
1'
0)
#366
0'
#367
b0000010011100111 $
b1100110011001001 %
b10 &
1'
b1100110011001001 +
#368
0'
#369
1'
#370
0'
#371
1'
#372
0'
#373
1'
#374
b11 #
0'
1)
#375
b10 #
b11 &
1'
#376
0'
0)
#377
b1100110011001001 $
b1101000110110000 %
b10 &
1'
b1101000110110000 +
#378
0'
#379
1'
#380
0'
#381
1'
#382
0'
#383
1'
#384
0'
#385
b11 #
1'
1)
#386
0'
#387
b10 #
b11 &
1'
0)
#388
0'
#389
b1101000110110000 $
b1001111001111001 %
b10 &
1'
b1001111001111001 +
#390
0'
#391
1'
#392
0'
#393
1'
#394
0'
#395
1'
#396
b11 #
0'
1)
#397
b10 #
b11 &
1'
#398
0'
0)
#399
b1001111001111001 $
b0111000000101001 %
b10 &
1'
b0111000000101001 +
#400
0'
#401
1'
#402
0'
#403
1'
#404
0'
#405
1'
#406
0'
#407
b11 #
1'
1)
#408
0'
#409
b10 #
b11 &
1'
0)
#410
0'
#411
b0111000000101001 $
b0000111010100010 %
b10 &
1'
b0000111010100010 +
#412
0'
#413
1'
#414
0'
#415
1'
#416
0'
#417
1'
#418
b11 #
0'
1)
#419
b10 #
b11 &
1'
#420
0'
0)
#421
b0000111010100010 $
b0111111011001011 %
b10 &
1'
b0111111011001011 +
#422
0'
#423
1'
#424
0'
#425
1'
#426
0'
#427
1'
#428
0'
#429
b11 #
1'
1)
#430
0'
#431
b10 #
b11 &
1'
0)
#432
0'
#433
b0111111011001011 $
b1000110101101101 %
b10 &
1'
b1000110101101101 +
#434
0'
#435
1'
#436
0'
#437
1'
#438
0'
#439
1'
#440
b11 #
0'
1)
#441
b10 #
b11 &
1'
#442
0'
0)
#443
b1000110101101101 $
b0000110000111000 %
b10 &
1'
b0000110000111000 +
#444
0'
#445
1'
#446
0'
#447
1'
#448
0'
#449
1'
#450
0'
#451
b11 #
1'
1)
#452
0'
#453
b10 #
b11 &
1'
0)
#454
0'
#455
b0000110000111000 $
b1001100110100101 %
b10 &
1'
b1001100110100101 +
#456
0'
#457
1'
#458
0'
#459
1'
#460
0'
#461
1'
#462
b11 #
0'
1)
#463
b10 #
b11 &
1'
#464
0'
0)
#465
b1001100110100101 $
b1010010111011101 %
b10 &
1'
b1010010111011101 +
#466
0'
#467
1'
#468
0'
#469
1'
#470
0'
#471
1'
#472
0'
#473
b11 #
1'
1)
#474
0'
#475
b10 #
b11 &
1'
0)
#476
0'
#477
b1010010111011101 $
b0011111110000010 %
b10 &
1'
b0011111110000010 +
#478
0'
#479
1'
#480
0'
#481
1'
#482
0'
#483
1'
#484
b11 #
0'
1)
#485
b10 #
b11 &
1'
#486
0'
0)
#487
b0011111110000010 $
b1110010101011111 %
b10 &
1'
b1110010101011111 +
#488
0'
#489
1'
#490
0'
#491
1'
#492
0'
#493
1'
#494
0'
#495
b11 #
1'
1)
#496
0'
#497
b10 #
b11 &
1'
0)
#498
0'
#499
b1110010101011111 $
b0010010011100001 %
b10 &
1'
b0010010011100001 +
#500
0'
#501
1'
#502
0'
#503
1'
#504
0'
#505
1'
#506
b11 #
0'
1)
#507
b10 #
b11 &
1'
#508
0'
0)
#509
b0010010011100001 $
b0000101001000000 %
b10 &
1'
b0000101001000000 +
#510
0'
#511
1'
#512
0'
#513
b00 #
b00 &
1'
0(
b0000000000000000 +
#514
0'
1(
#515
b0000000000000010 $
1'
#516
0'
#517
b01 #
1'
1)
#518
0'
#519
b01 &
1'
0)
b0000000000000010 +
#520
0'
#521
b0000000000000010 %
1'
#522
0'
#523
1'
#524
0'
#525
1'
#526
0'
#527
1'
#528
b10 #
0'
1)
#529
b11 #
b10 &
1'
#530
b10 #
0'
0)
#531
1'
#532
0'
#533
1'
#534
0'
#535
1'
#536
0'
#537
1'
#538
0'
#539
b11 #
1'
1)
#540
0'
#541
b10 #
b11 &
1'
0)
#542
0'
#543
b0000000000000100 %
b10 &
1'
b0000000000000100 +
#544
0'
#545
1'
#546
0'
#547
1'
#548
0'
#549
1'
#550
b11 #
0'
1)
#551
b10 #
b11 &
1'
#552
0'
0)
#553
b0000000000000100 $
b0000000000000110 %
b10 &
1'
b0000000000000110 +
#554
0'
#555
1'
#556
0'
#557
1'
#558
0'
#559
1'
#560
0'
#561
b11 #
1'
1)
#562
0'
#563
b10 #
b11 &
1'
0)
#564
0'
#565
b0000000000000110 $
b0000000000001010 %
b10 &
1'
b0000000000001010 +
#566
0'
#567
1'
#568
0'
#569
1'
#570
0'
#571
1'
#572
b11 #
0'
1)
#573
b10 #
b11 &
1'
#574
0'
0)
#575
b0000000000001010 $
b0000000000010000 %
b10 &
1'
b0000000000010000 +
#576
0'
#577
1'
#578
0'
#579
1'
#580
0'
#581
1'
#582
0'
#583
b11 #
1'
1)
#584
0'
#585
b10 #
b11 &
1'
0)
#586
0'
#587
b0000000000010000 $
b0000000000011010 %
b10 &
1'
b0000000000011010 +
#588
0'
#589
1'
#590
0'
#591
1'
#592
0'
#593
1'
#594
b11 #
0'
1)
#595
b10 #
b11 &
1'
#596
0'
0)
#597
b0000000000011010 $
b0000000000101010 %
b10 &
1'
b0000000000101010 +
#598
0'
#599
1'
#600
0'
#601
1'
#602
0'
#603
1'
#604
0'
#605
b11 #
1'
1)
#606
0'
#607
b10 #
b11 &
1'
0)
#608
0'
#609
b0000000000101010 $
b0000000001000100 %
b10 &
1'
b0000000001000100 +
#610
0'
#611
1'
#612
0'
#613
1'
#614
0'
#615
1'
#616
b11 #
0'
1)
#617
b10 #
b11 &
1'
#618
0'
0)
#619
b0000000001000100 $
b0000000001101110 %
b10 &
1'
b0000000001101110 +
#620
0'
#621
1'
#622
0'
#623
1'
#624
0'
#625
1'
#626
0'
#627
b11 #
1'
1)
#628
0'
#629
b10 #
b11 &
1'
0)
#630
0'
#631
b0000000001101110 $
b0000000010110010 %
b10 &
1'
b0000000010110010 +
#632
0'
#633
1'
#634
0'
#635
1'
#636
0'
#637
1'
#638
b11 #
0'
1)
#639
b10 #
b11 &
1'
#640
0'
0)
#641
b0000000010110010 $
b0000000100100000 %
b10 &
1'
b0000000100100000 +
#642
0'
#643
1'
#644
0'
#645
1'
#646
0'
#647
1'
#648
0'
#649
b11 #
1'
1)
#650
0'
#651
b10 #
b11 &
1'
0)
#652
0'
#653
b0000000100100000 $
b0000000111010010 %
b10 &
1'
b0000000111010010 +
#654
0'
#655
1'
#656
0'
#657
1'
#658
0'
#659
1'
#660
b11 #
0'
1)
#661
b10 #
b11 &
1'
#662
0'
0)
#663
b0000000111010010 $
b0000001011110010 %
b10 &
1'
b0000001011110010 +
#664
0'
#665
1'
#666
0'
#667
1'
#668
0'
#669
1'
#670
0'
#671
b11 #
1'
1)
#672
0'
#673
b10 #
b11 &
1'
0)
#674
0'
#675
b0000001011110010 $
b0000010011000100 %
b10 &
1'
b0000010011000100 +
#676
0'
#677
1'
#678
0'
#679
1'
#680
0'
#681
1'
#682
b11 #
0'
1)
#683
b10 #
b11 &
1'
#684
0'
0)
#685
b0000010011000100 $
b0000011110110110 %
b10 &
1'
b0000011110110110 +
#686
0'
#687
1'
#688
0'
#689
1'
#690
0'
#691
1'
#692
0'
#693
b11 #
1'
1)
#694
0'
#695
b10 #
b11 &
1'
0)
#696
0'
#697
b0000011110110110 $
b0000110001111010 %
b10 &
1'
b0000110001111010 +
#698
0'
#699
1'
#700
0'
#701
1'
#702
0'
#703
1'
#704
b11 #
0'
1)
#705
b10 #
b11 &
1'
#706
0'
0)
#707
b0000110001111010 $
b0001010000110000 %
b10 &
1'
b0001010000110000 +
#708
0'
#709
1'
#710
0'
#711
1'
#712
0'
#713
1'
#714
0'
#715
b11 #
1'
1)
#716
0'
#717
b10 #
b11 &
1'
0)
#718
0'
#719
b0001010000110000 $
b0010000010101010 %
b10 &
1'
b0010000010101010 +
#720
0'
#721
1'
#722
0'
#723
1'
#724
0'
#725
1'
#726
b11 #
0'
1)
#727
b10 #
b11 &
1'
#728
0'
0)
#729
b0010000010101010 $
b0011010011011010 %
b10 &
1'
b0011010011011010 +
#730
0'
#731
1'
#732
0'
#733
1'
#734
0'
#735
1'
#736
0'
#737
b11 #
1'
1)
#738
0'
#739
b10 #
b11 &
1'
0)
#740
0'
#741
b0011010011011010 $
b0101010110000100 %
b10 &
1'
b0101010110000100 +
#742
0'
#743
1'
#744
0'
#745
1'
#746
0'
#747
1'
#748
b11 #
0'
1)
#749
b10 #
b11 &
1'
#750
0'
0)
#751
b0101010110000100 $
b1000101001011110 %
b10 &
1'
b1000101001011110 +
#752
0'
#753
1'
#754
0'
#755
1'
#756
0'
#757
1'
#758
0'
#759
b11 #
1'
1)
#760
0'
#761
b10 #
b11 &
1'
0)
#762
0'
#763
b1000101001011110 $
b1101111111100010 %
b10 &
1'
b1101111111100010 +
#764
0'
#765
1'
#766
0'
#767
1'
#768
0'
#769
1'
#770
b11 #
0'
1)
#771
b10 #
b11 &
1'
#772
0'
0)
#773
b1101111111100010 $
b0110101001000000 %
b10 &
1'
b0110101001000000 +
#774
0'
#775
1'
#776
0'
#777
1'
#778
0'
#779
1'
#780
0'
#781
b11 #
1'
1)
#782
0'
#783
b10 #
b11 &
1'
0)
#784
0'
#785
b0110101001000000 $
b0100101000100010 %
b10 &
1'
b0100101000100010 +
#786
0'
#787
1'
#788
0'
#789
1'
#790
0'
#791
1'
#792
b11 #
0'
1)
#793
b10 #
b11 &
1'
#794
0'
0)
#795
b0100101000100010 $
b1011010001100010 %
b10 &
1'
b1011010001100010 +
#796
0'
#797
1'
#798
0'
#799
1'
#800
0'
#801
1'
#802
0'
#803
b11 #
1'
1)
#804
0'
#805
b10 #
b11 &
1'
0)
#806
0'
#807
b1011010001100010 $
b1111111010000100 %
b10 &
1'
b1111111010000100 +
#808
0'
#809
1'
#810
0'
#811
1'
#812
0'
#813
1'
#814
b11 #
0'
1)
#815
b10 #
b11 &
1'
#816
0'
0)
#817
b1111111010000100 $
b1011001011100110 %
b10 &
1'
b1011001011100110 +
#818
0'
#819
1'
#820
0'
#821
1'
#822
0'
#823
1'
#824
0'
#825
b11 #
1'
1)
#826
0'
#827
b10 #
b11 &
1'
0)
#828
0'
#829
b1011001011100110 $
b1011000101101010 %
b10 &
1'
b1011000101101010 +
#830
0'
#831
1'
#832
0'
#833
1'
#834
0'
#835
1'
#836
b11 #
0'
1)
#837
b10 #
b11 &
1'
#838
0'
0)
#839
b1011000101101010 $
b0110010001010000 %
b10 &
1'
b0110010001010000 +
#840
0'
#841
1'
#842
0'
#843
1'
#844
0'
#845
1'
#846
0'
#847
b11 #
1'
1)
#848
0'
#849
b10 #
b11 &
1'
0)
#850
0'
#851
b0110010001010000 $
b0001010110111010 %
b10 &
1'
b0001010110111010 +
#852
0'
#853
1'
#854
0'
#855
1'
#856
0'
#857
1'
#858
b11 #
0'
1)
#859
b10 #
b11 &
1'
#860
0'
0)
#861
b0001010110111010 $
b0111101000001010 %
b10 &
1'
b0111101000001010 +
#862
0'
#863
1'
#864
0'
#865
1'
#866
0'
#867
1'
#868
0'
#869
b11 #
1'
1)
#870
0'
#871
b10 #
b11 &
1'
0)
#872
0'
#873
b0111101000001010 $
b1000111111000100 %
b10 &
1'
b1000111111000100 +
#874
0'
#875
1'
#876
0'
#877
1'
#878
0'
#879
1'
#880
b11 #
0'
1)
#881
b10 #
b11 &
1'
#882
0'
0)
#883
b1000111111000100 $
b0000100111001110 %
b10 &
1'
b0000100111001110 +
#884
0'
#885
1'
#886
0'
#887
1'
#888
0'
#889
1'
#890
0'
#891
b11 #
1'
1)
#892
0'
#893
b10 #
b11 &
1'
0)
#894
0'
#895
b0000100111001110 $
b1001100110010010 %
b10 &
1'
b1001100110010010 +
#896
0'
#897
1'
#898
0'
#899
1'
#900
0'
#901
1'
#902
b11 #
0'
1)
#903
b10 #
b11 &
1'
#904
0'
0)
#905
b1001100110010010 $
b1010001101100000 %
b10 &
1'
b1010001101100000 +
#906
0'
#907
1'
#908
0'
#909
1'
#910
0'
#911
1'
#912
0'
#913
b11 #
1'
1)
#914
0'
#915
b10 #
b11 &
1'
0)
#916
0'
#917
b1010001101100000 $
b0011110011110010 %
b10 &
1'
b0011110011110010 +
#918
0'
#919
1'
#920
0'
#921
1'
#922
0'
#923
1'
#924
b11 #
0'
1)
#925
b10 #
b11 &
1'
#926
0'
0)
#927
b0011110011110010 $
b1110000001010010 %
b10 &
1'
b1110000001010010 +
#928
0'
#929
1'
#930
0'
#931
1'
#932
0'
#933
1'
#934
0'
#935
b11 #
1'
1)
#936
0'
#937
b10 #
b11 &
1'
0)
#938
0'
#939
b1110000001010010 $
b0001110101000100 %
b10 &
1'
b0001110101000100 +
#940
0'
#941
1'
#942
0'
#943
1'
#944
0'
#945
1'
#946
b11 #
0'
1)
#947
b10 #
b11 &
1'
#948
0'
0)
#949
b0001110101000100 $
b1111110110010110 %
b10 &
1'
b1111110110010110 +
#950
0'
#951
1'
#952
0'
#953
1'
#954
0'
#955
1'
#956
0'
#957
b11 #
1'
1)
#958
0'
#959
b10 #
b11 &
1'
0)
#960
0'
#961
b1111110110010110 $
b0001101011011010 %
b10 &
1'
b0001101011011010 +
#962
0'
#963
1'
#964
0'
#965
1'
#966
0'
#967
1'
#968
b11 #
0'
1)
#969
b10 #
b11 &
1'
#970
0'
0)
#971
b0001101011011010 $
b0001100001110000 %
b10 &
1'
b0001100001110000 +
#972
0'
#973
1'
#974
0'
#975
1'
#976
0'
#977
1'
#978
0'
#979
b11 #
1'
1)
#980
0'
#981
b10 #
b11 &
1'
0)
#982
0'
#983
b0001100001110000 $
b0011001101001010 %
b10 &
1'
b0011001101001010 +
#984
0'
#985
1'
#986
0'
#987
1'
#988
0'
#989
1'
#990
b11 #
0'
1)
#991
b10 #
b11 &
1'
#992
0'
0)
#993
b0011001101001010 $
b0100101110111010 %
b10 &
1'
b0100101110111010 +
#994
0'
#995
1'
#996
0'
#997
1'
#998
0'
#999
1'
#1000
0'
#1001
b11 #
1'
1)
#1002
0'
#1003
b10 #
b11 &
1'
0)
#1004
0'
#1005
b0100101110111010 $
b0111111100000100 %
b10 &
1'
b0111111100000100 +
#1006
0'
#1007
1'
#1008
0'
#1009
1'
#1010
0'
#1011
1'
#1012
b11 #
0'
1)
#1013
b10 #
b11 &
1'
#1014
0'
0)
#1015
b0111111100000100 $
b1100101010111110 %
b10 &
1'
b1100101010111110 +
#1016
0'
#1017
1'
#1018
0'
#1019
1'
#1020
0'
#1021
1'
#1022
0'
#1023
b11 #
1'
1)
