计算机组成原理实验/lab2/srcs/register_file.v
`timescale 1ns / 1ps
//////////////////////////////////////////////////////////////////////////////////
// Company:
// Engineer:
//
// Create Date: 2022/03/27 13:52:35
// Design Name:
// Module Name: register_file
// Project Name:
// Target Devices:
// Tool Versions:
// Description:
//
// Dependencies:
//
// Revision:
// Revision 0.01 - File Created
// Additional Comments:
//
//////////////////////////////////////////////////////////////////////////////////


module register_file #(
        parameter AW = 5,
        parameter DW = 32)
    (input  clk,
     input [AW-1: 0] ra0,   // 异步读1地址
     input [AW-1: 0] ra1,   // 异步读2地址
     output [DW-1:0] rd0,   // 异步读1值
     output [DW-1:0] rd1,   // 异步读2值
     input [AW-1: 0] wa,    // 同步写地址
     input [DW-1: 0] wd,    // 同步写值
     input we);             // 同步写使能

    reg [DW-1: 0] rf[0: (1<<AW)-1];
    assign rd0 = (ra0 == wa) && we ? wd : rf[ra0];
    assign rd1 = (ra1 == wa) && we ? wd : rf[ra1];

    always @(*) begin
        rf[0] = 0;
    end

    always @(posedge clk)
        if (wa !== 0 && we)
            rf[wa] <= wd;
endmodule

计算机组成原理实验/lab2/srcs/register_file.vcd
$version Generated by VerilatedVcd $end
$date Sun Mar 27 14:55:15 2022
 $end
$timescale   1ns $end

 $scope module TOP $end
  $var wire  1 C clk $end
  $var wire  5 D ra0 [4:0] $end
  $var wire  5 E ra1 [4:0] $end
  $var wire 32 F rd0 [31:0] $end
  $var wire 32 G rd1 [31:0] $end
  $var wire  5 H wa [4:0] $end
  $var wire 32 I wd [31:0] $end
  $var wire  1 J we $end
  $scope module register_file $end
   $var wire 32 K AW [31:0] $end
   $var wire 32 L DW [31:0] $end
   $var wire  1 C clk $end
   $var wire  5 D ra0 [4:0] $end
   $var wire  5 E ra1 [4:0] $end
   $var wire 32 F rd0 [31:0] $end
   $var wire 32 G rd1 [31:0] $end
   $var wire 32 # rf(0) [31:0] $end
   $var wire 32 $ rf(1) [31:0] $end
   $var wire 32 - rf(10) [31:0] $end
   $var wire 32 . rf(11) [31:0] $end
   $var wire 32 / rf(12) [31:0] $end
   $var wire 32 0 rf(13) [31:0] $end
   $var wire 32 1 rf(14) [31:0] $end
   $var wire 32 2 rf(15) [31:0] $end
   $var wire 32 3 rf(16) [31:0] $end
   $var wire 32 4 rf(17) [31:0] $end
   $var wire 32 5 rf(18) [31:0] $end
   $var wire 32 6 rf(19) [31:0] $end
   $var wire 32 % rf(2) [31:0] $end
   $var wire 32 7 rf(20) [31:0] $end
   $var wire 32 8 rf(21) [31:0] $end
   $var wire 32 9 rf(22) [31:0] $end
   $var wire 32 : rf(23) [31:0] $end
   $var wire 32 ; rf(24) [31:0] $end
   $var wire 32 < rf(25) [31:0] $end
   $var wire 32 = rf(26) [31:0] $end
   $var wire 32 > rf(27) [31:0] $end
   $var wire 32 ? rf(28) [31:0] $end
   $var wire 32 @ rf(29) [31:0] $end
   $var wire 32 & rf(3) [31:0] $end
   $var wire 32 A rf(30) [31:0] $end
   $var wire 32 B rf(31) [31:0] $end
   $var wire 32 ' rf(4) [31:0] $end
   $var wire 32 ( rf(5) [31:0] $end
   $var wire 32 ) rf(6) [31:0] $end
   $var wire 32 * rf(7) [31:0] $end
   $var wire 32 + rf(8) [31:0] $end
   $var wire 32 , rf(9) [31:0] $end
   $var wire  5 H wa [4:0] $end
   $var wire 32 I wd [31:0] $end
   $var wire  1 J we $end
  $upscope $end
 $upscope $end
$enddefinitions $end


#0
b00000000000000000000000000000000 #
b00000000000000000000000000000000 $
b00000000000000000000000000000000 %
b00000000000000000000000000000000 &
b00000000000000000000000000000000 '
b00000000000000000000000000000000 (
b00000000000000000000000000000000 )
b00000000000000000000000000000000 *
b00000000000000000000000000000000 +
b00000000000000000000000000000000 ,
b00000000000000000000000000000000 -
b00000000000000000000000000000000 .
b00000000000000000000000000000000 /
b00000000000000000000000000000000 0
b00000000000000000000000000000000 1
b00000000000000000000000000000000 2
b00000000000000000000000000000000 3
b00000000000000000000000000000000 4
b00000000000000000000000000000000 5
b00000000000000000000000000000000 6
b00000000000000000000000000000000 7
b00000000000000000000000000000000 8
b00000000000000000000000000000000 9
b00000000000000000000000000000000 :
b00000000000000000000000000000000 ;
b00000000000000000000000000000000 <
b00000000000000000000000000000000 =
b00000000000000000000000000000000 >
b00000000000000000000000000000000 ?
b00000000000000000000000000000000 @
b00000000000000000000000000000000 A
b00000000000000000000000000000000 B
1C
b00000 D
b00001 E
b00000000000000000000000000000000 F
b00000000000000000000000000000000 G
b00001 H
b00000000000000000000000000000000 I
0J
b00000000000000000000000000000101 K
b00000000000000000000000000100000 L
#1
#2
#3
#4
1J
#5
0C
b00001 D
b00010 E
b01101011100010110100010101100111 G
b00010 H
b01101011100010110100010101100111 I
#6
#7
#8
#9
#10
b01101011100010110100010101100111 %
1C
#11
#12
#13
0J
#14
#15
0C
b00010 D
b00011 E
b01101011100010110100010101100111 F
b00000000000000000000000000000000 G
b00011 H
b00110010011110110010001111000110 I
#16
#17
#18
#19
#20
1C
#21
#22
#23
#24
b00110010011110110010001111000110 G
1J
#25
0C
b00011 D
b00100 E
b00000000000000000000000000000000 F
b01100100001111001001100001101001 G
b00100 H
b01100100001111001001100001101001 I
#26
#27
#28
#29
#30
b01100100001111001001100001101001 '
1C
#31
#32
#33
0J
#34
#35
0C
b00100 D
b00101 E
b01100100001111001001100001101001 F
b00000000000000000000000000000000 G
b00101 H
b01100110001100110100100001110011 I
#36
#37
#38
#39
#40
1C
#41
#42
#43
#44
b01100110001100110100100001110011 G
1J
#45
0C
b00101 D
b00110 E
b00000000000000000000000000000000 F
b01110100101100001101110001010001 G
b00110 H
b01110100101100001101110001010001 I
#46
#47
#48
#49
#50
b01110100101100001101110001010001 )
1C
#51
#52
#53
0J
#54
#55
0C
b00110 D
b00111 E
b01110100101100001101110001010001 F
b00000000000000000000000000000000 G
b00111 H
b00011001010010010101110011111111 I
#56
#57
#58
#59
#60
1C
#61
#62
#63
#64
b00011001010010010101110011111111 G
1J
#65
0C
b00111 D
b01000 E
b00000000000000000000000000000000 F
b00101010111010001001010001001010 G
b01000 H
b00101010111010001001010001001010 I
#66
#67
#68
#69
#70
b00101010111010001001010001001010 +
1C
#71
#72
#73
0J
#74
#75
0C
b01000 D
b01001 E
b00101010111010001001010001001010 F
b00000000000000000000000000000000 G
b01001 H
b01100010010101010101100011101100 I
#76
#77
#78
#79
#80
1C
#81
#82
#83
#84
b01100010010101010101100011101100 G
1J
#85
0C
b01001 D
b01010 E
b00000000000000000000000000000000 F
b00100011100011100001111100101001 G
b01010 H
b00100011100011100001111100101001 I
#86
#87
#88
#89
#90
b00100011100011100001111100101001 -
1C
#91
#92
#93
0J
#94
#95
0C
b01010 D
b01011 E
b00100011100011100001111100101001 F
b00000000000000000000000000000000 G
b01011 H
b01000110111010000111110011001101 I
#96
#97
#98
#99
#100
1C
b00000 E
#101
#102
#103
#104
1J
#105
0C
b01011 D
b00000000000000000000000000000000 F
b01100 H
b00111101000110110101100010111010 I
#106
#107
#108
#109
#110
b00111101000110110101100010111010 /
1C
b00001 E
#111
#112
#113
0J
#114
#115
0C
b01100 D
b00111101000110110101100010111010 F
b01101 H
b01010000011111101101011110101011 I
#116
#117
#118
#119
#120
1C
b00010 E
b01101011100010110100010101100111 G
#121
#122
#123
#124
1J
#125
0C
b01101 D
b00000000000000000000000000000000 F
b01110 H
b00101110101100010100000111110010 I
#126
#127
#128
#129
#130
b00101110101100010100000111110010 1
1C
b00011 E
b00000000000000000000000000000000 G
#131
#132
#133
0J
#134
#135
0C
b01110 D
b00101110101100010100000111110010 F
b01111 H
b01000001101101110001111011111011 I
#136
#137
#138
#139
#140
1C
b00100 E
b01100100001111001001100001101001 G
#141
#142
#143
#144
1J
#145
0C
b01111 D
b00000000000000000000000000000000 F
b10000 H
b01111001111000101010100111100011 I
#146
#147
#148
#149
#150
b01111001111000101010100111100011 3
1C
b00101 E
b00000000000000000000000000000000 G
#151
#152
#153
0J
#154
#155
0C
b10000 D
b01111001111000101010100111100011 F
b10001 H
b01110101010001011110000101000110 I
#156
#157
#158
#159
#160
1C
b00110 E
b01110100101100001101110001010001 G
#161
#162
#163
#164
1J
#165
0C
b10001 D
b00000000000000000000000000000000 F
b10010 H
b01010001010111110000000001111100 I
#166
#167
#168
#169
#170
b01010001010111110000000001111100 5
1C
b00111 E
b00000000000000000000000000000000 G
#171
#172
#173
0J
#174
#175
0C
b10010 D
b01010001010111110000000001111100 F
b10011 H
b01011011110100000110001011000010 I
#176
#177
#178
#179
#180
1C
b01000 E
b00101010111010001001010001001010 G
#181
#182
#183
#184
1J
#185
0C
b10011 D
b00000000000000000000000000000000 F
b10100 H
b00010010001000000000100001010100 I
#186
#187
#188
#189
#190
b00010010001000000000100001010100 7
1C
b01001 E
b00000000000000000000000000000000 G
#191
#192
#193
0J
#194
#195
0C
b10100 D
b00010010001000000000100001010100 F
b10101 H
b01001101101100010010011111111000 I
